ndp_versioncontrol/__init__.py
ndp_versioncontrol/generate_backup_sql.py
ndp_app_versioncontrol-2.5.dist-info/METADATA
ndp_app_versioncontrol-2.5.dist-info/WHEEL
ndp_app_versioncontrol-2.5.dist-info/top_level.txt
ndp_app_versioncontrol-2.5.dist-info/RECORD
