Metadata-Version: 2.1
Name: ndp-app-versioncontrol
Version: 2.5
Summary: Version Control Mechanism for Zetaris Platform (https://www.zetaris.com/)
Home-page: https://github.com/zetaris/versioncontrol
Author: Harshal Shah
Author-email: harshal.shah@zetaris.com
License: Proprietary
Classifier: Programming Language :: Python :: 3
Classifier: License :: Other/Proprietary License
Classifier: Operating System :: OS Independent
Requires-Dist: pandas
Requires-Dist: jaydebeapi
Requires-Dist: numpy
Requires-Dist: pycryptodomex
Requires-Dist: getpass4
Requires-Dist: pyyaml
Requires-Dist: sqlalchemy
